application_example/__init__.py
application_example/example.py
keepcodingtest-0.0.1.dist-info/METADATA
keepcodingtest-0.0.1.dist-info/WHEEL
keepcodingtest-0.0.1.dist-info/top_level.txt
keepcodingtest-0.0.1.dist-info/RECORD
