Metadata-Version: 2.1
Name: keepcodingtest
Version: 0.0.1
Summary: Un ejemplo
Author: keepcoder
Author-email: rmmonteagudo@gmail.com
License: UNKNOWN
Platform: UNKNOWN
Requires-Python: >=3.6
Requires-Dist: build
Requires-Dist: twine
